[
    {
        "name": "Devicons.Hibernate.Plain",
        "svg": "https://raw.githubusercontent.com/devicons/devicon/v2.16.0/icons/hibernate/hibernate-plain.svg"
    },
    {
        "name": "Devicons.Hibernate.OriginalWordmark",
        "svg": "https://raw.githubusercontent.com/devicons/devicon/v2.16.0/icons/hibernate/hibernate-original-wordmark.svg"
    },
    {
        "name": "Devicons.Hibernate.PlainWordmark",
        "svg": "https://raw.githubusercontent.com/devicons/devicon/v2.16.0/icons/hibernate/hibernate-plain-wordmark.svg"
    },
    {
        "name": "Devicons.Hibernate.Original",
        "svg": "https://raw.githubusercontent.com/devicons/devicon/v2.16.0/icons/hibernate/hibernate-original.svg"
    }
]