[
    {
        "name": "Devicons.Chrome.PlainWordmark",
        "svg": "https://raw.githubusercontent.com/devicons/devicon/v2.16.0/icons/chrome/chrome-plain-wordmark.svg"
    },
    {
        "name": "Devicons.Chrome.Plain",
        "svg": "https://raw.githubusercontent.com/devicons/devicon/v2.16.0/icons/chrome/chrome-plain.svg"
    },
    {
        "name": "Devicons.Chrome.OriginalWordmark",
        "svg": "https://raw.githubusercontent.com/devicons/devicon/v2.16.0/icons/chrome/chrome-original-wordmark.svg"
    },
    {
        "name": "Devicons.Chrome.Original",
        "svg": "https://raw.githubusercontent.com/devicons/devicon/v2.16.0/icons/chrome/chrome-original.svg"
    }
]