[
    {
        "name": "Devicons.Photoshop.Original",
        "svg": "https://raw.githubusercontent.com/devicons/devicon/v2.16.0/icons/photoshop/photoshop-original.svg"
    },
    {
        "name": "Devicons.Photoshop.Line",
        "svg": "https://raw.githubusercontent.com/devicons/devicon/v2.16.0/icons/photoshop/photoshop-line.svg"
    },
    {
        "name": "Devicons.Photoshop.Plain",
        "svg": "https://raw.githubusercontent.com/devicons/devicon/v2.16.0/icons/photoshop/photoshop-plain.svg"
    }
]